fh_flowbite/__init__.py
fh_flowbite/flowbite.py
fh_flowbite/modal.py
fh_flowbite-0.0.1.dist-info/LICENSE
fh_flowbite-0.0.1.dist-info/METADATA
fh_flowbite-0.0.1.dist-info/WHEEL
fh_flowbite-0.0.1.dist-info/top_level.txt
fh_flowbite-0.0.1.dist-info/RECORD
